LICENSE
README.md
setup.cfg
setup.py
tests/__init__.py
tests/interpretation/__init__.py
tests/interpretation/example_level/__init__.py
tests/interpretation/example_level/test_feature_similarity.py
tests/interpretation/example_level/test_gradient_similarity.py
tests/interpretation/example_level/test_reppoint.py
trustai/__init__.py
trustai/demo/__init__.py
trustai/demo/demo.py
trustai/demo/utils.py
trustai/evaluation/__init__.py
trustai/evaluation/evaluator.py
trustai/interpretation/__init__.py
trustai/interpretation/base_interpret.py
trustai/interpretation/python_utils.py
trustai/interpretation/example_level/__init__.py
trustai/interpretation/example_level/common/__init__.py
trustai/interpretation/example_level/common/data_class.py
trustai/interpretation/example_level/common/utils.py
trustai/interpretation/example_level/method/__init__.py
trustai/interpretation/example_level/method/example_base_interpreter.py
trustai/interpretation/example_level/method/feature_similarity.py
trustai/interpretation/example_level/method/gradient_similarity.py
trustai/interpretation/example_level/method/representer_point.py
trustai/interpretation/token_level/__init__.py
trustai/interpretation/token_level/common/__init__.py
trustai/interpretation/token_level/common/postprocess_attribution.py
trustai/interpretation/token_level/common/predict_functions.py
trustai/interpretation/token_level/data_processor/__init__.py
trustai/interpretation/token_level/data_processor/data_class.py
trustai/interpretation/token_level/data_processor/visualizer.py
trustai/interpretation/token_level/method/__init__.py
trustai/interpretation/token_level/method/attention.py
trustai/interpretation/token_level/method/base_interpret.py
trustai/interpretation/token_level/method/gradient_shap.py
trustai/interpretation/token_level/method/integrated_gradients.py
trustai/interpretation/token_level/method/lime.py
trustai/interpretation/token_level/method/norm_lime.py
trustai_new.egg-info/PKG-INFO
trustai_new.egg-info/SOURCES.txt
trustai_new.egg-info/dependency_links.txt
trustai_new.egg-info/not-zip-safe
trustai_new.egg-info/requires.txt
trustai_new.egg-info/top_level.txt