Metadata-Version: 2.1
Name: trustai-new
Version: 0.2.0
Summary: New TrusiAI supported for paddle >= 2.5 from baidu TrustAI
Home-page: https://github.com/NeptuneZhao/TrusiAI-New
Author: Baidu NLP / HalfCooler6182(NeptuneZhao)
Author-email: nlp-parser@baidu.com / qq1836143240@outlook.com
License: Apache License 2.0
Keywords: baidu,TrustAI,interpretation
Classifier: Programming Language :: Python :: 3
Classifier: Programming Language :: Python :: 3.12
Classifier: License :: OSI Approved :: Apache Software License
Classifier: Operating System :: OS Independent
License-File: LICENSE
Requires-Dist: scikit-learn
Requires-Dist: numpy
Requires-Dist: tqdm
Requires-Dist: matplotlib
Requires-Dist: IPython
